chess_env_rl.cpython-313-x86_64-linux-gnu.so
chess_env_rl-0.0.2.dist-info/METADATA
chess_env_rl-0.0.2.dist-info/WHEEL
chess_env_rl-0.0.2.dist-info/top_level.txt
chess_env_rl-0.0.2.dist-info/RECORD
chess_env_rl-0.0.2.dist-info/licenses/LICENSE.md
